setup.cfg
setup.py
gaia_uplift/__init__.py
gaia_uplift/branch_logic.py
gaia_uplift/bugdb.py
gaia_uplift/bzapi.py
gaia_uplift/config.json
gaia_uplift/configuration.py
gaia_uplift/driver.py
gaia_uplift/find_commits.py
gaia_uplift/ghapi.py
gaia_uplift/git.py
gaia_uplift/merge_hd.py
gaia_uplift/reporting.py
gaia_uplift/uplift.py
gaia_uplift/util.py
uplift.egg-info/PKG-INFO
uplift.egg-info/SOURCES.txt
uplift.egg-info/dependency_links.txt
uplift.egg-info/entry_points.txt
uplift.egg-info/requires.txt
uplift.egg-info/top_level.txt