Metadata-Version: 1.0
Name: uplift
Version: 4
Summary: This is a program used to uplift bugs from Gaia's master branch to release branches
Home-page: https://github.com/mozilla-b2g/uplift
Author: John Ford
Author-email: john@johnford.info
License: UNKNOWN
Keywords: b2g uplift git mozilla firefoxos
Platform: UNKNOWN
